egobench/__init__.py
egobench-0.0.1.dist-info/METADATA
egobench-0.0.1.dist-info/WHEEL
egobench-0.0.1.dist-info/top_level.txt
egobench-0.0.1.dist-info/RECORD
